snek5000/__init__.py
snek5000/_version.py
snek5000/clusters.py
snek5000/config.py
snek5000/const.py
snek5000/info.py
snek5000/log.py
snek5000/magic.py
snek5000/make.py
snek5000/operators.py
snek5000/params.py
snek5000/output/__init__.py
snek5000/output/base.py
snek5000/output/history_points.py
snek5000/output/phys_fields.py
snek5000/output/print_stdout.py
snek5000/output/remaining_clock_time.py
snek5000/output/simple_csv.py
snek5000/output/spatial_means.py
snek5000/output/readers/__init__.py
snek5000/output/readers/pymech_.py
snek5000/output/readers/try_paraview_.py
snek5000/resources/SIZE.j2
snek5000/resources/__init__.py
snek5000/resources/box.j2
snek5000/resources/compile.sh.j2
snek5000/resources/compiler.smk
snek5000/resources/default_configfile.yml
snek5000/resources/internal.smk
snek5000/resources/io.smk
snek5000/resources/makefile_usr.inc.j2
snek5000/resources/nek5000.smk
snek5000/solvers/__init__.py
snek5000/solvers/base.py
snek5000/solvers/kth.py
snek5000/util/__init__.py
snek5000/util/archive.py
snek5000/util/console.py
snek5000/util/files.py
snek5000/util/gfortran_log.py
snek5000/util/restart.py
snek5000/util/smake.py
snek5000-0.9.2.dist-info/LICENSE
snek5000-0.9.2.dist-info/METADATA
snek5000-0.9.2.dist-info/WHEEL
snek5000-0.9.2.dist-info/entry_points.txt
snek5000-0.9.2.dist-info/top_level.txt
snek5000-0.9.2.dist-info/RECORD
