Metadata-Version: 2.1
Name: snek5000
Version: 0.9.2
Summary: Python framework for Nek5000
Home-page: https://github.com/snek5000/snek5000
Author: Ashwin Vishnu Mohanan
Author-email: ashwinvis+gh@protonmail.com
License: BSD-3-Clause
Project-URL: Sponsor, https://fluid.quest/pages/sponsors.html
Project-URL: Bug Tracker, https://github.com/snek5000/snek5000/issues
Project-URL: Documentation, https://snek5000.readthedocs.io
Project-URL: Changelog, https://snek5000.readthedocs.io/en/latest/CHANGELOG.html
Classifier: Development Status :: 5 - Production/Stable
Classifier: Intended Audience :: Science/Research
Classifier: License :: OSI Approved :: BSD License
Classifier: Natural Language :: English
Classifier: Programming Language :: Python :: 3 :: Only
Classifier: Programming Language :: Python :: 3.8
Classifier: Programming Language :: Python :: 3.9
Classifier: Programming Language :: Python :: 3.10
Classifier: Topic :: Scientific/Engineering
Requires-Python: >=3.8
License-File: LICENSE
Requires-Dist: snakemake >=7.15.2
Requires-Dist: fluiddyn >=0.4.0
Requires-Dist: fluidsim-core >=0.7.2
Requires-Dist: pymech >=1.5.0
Requires-Dist: pandas
Requires-Dist: jinja2
Requires-Dist: inflection
Requires-Dist: pyyaml
Requires-Dist: filelock
Provides-Extra: dev
Requires-Dist: sphinx ; extra == 'dev'
Requires-Dist: myst-parser ; extra == 'dev'
Requires-Dist: myst-nb ; extra == 'dev'
Requires-Dist: docutils <0.18,>=0.14 ; extra == 'dev'
Requires-Dist: sphinx-autobuild ; extra == 'dev'
Requires-Dist: sphinx-copybutton ; extra == 'dev'
Requires-Dist: sphinx-inline-tabs ; extra == 'dev'
Requires-Dist: furo ; extra == 'dev'
Requires-Dist: breathe ; extra == 'dev'
Requires-Dist: setuptools-scm ; extra == 'dev'
Requires-Dist: nbdime ; extra == 'dev'
Requires-Dist: pygments >=2.4.1 ; extra == 'dev'
Requires-Dist: linkify-it-py ; extra == 'dev'
Requires-Dist: scipy ; extra == 'dev'
Requires-Dist: snek5000-tgv ; extra == 'dev'
Requires-Dist: snek5000-phill ; extra == 'dev'
Requires-Dist: snek5000-cbox ; extra == 'dev'
Requires-Dist: nox ; extra == 'dev'
Requires-Dist: pytest ; extra == 'dev'
Requires-Dist: coverage[toml] ; extra == 'dev'
Requires-Dist: pytest-cov ; extra == 'dev'
Requires-Dist: pytest-datadir ; extra == 'dev'
Requires-Dist: pytest-mock ; extra == 'dev'
Requires-Dist: ipython ; extra == 'dev'
Requires-Dist: click ; extra == 'dev'
Requires-Dist: rich ; extra == 'dev'
Requires-Dist: pdbpp ; extra == 'dev'
Requires-Dist: python-lsp-server ; extra == 'dev'
Requires-Dist: fortran-language-server ; extra == 'dev'
Requires-Dist: pre-commit >=2.9.0 ; extra == 'dev'
Requires-Dist: twine ; extra == 'dev'
Requires-Dist: build ; extra == 'dev'
Provides-Extra: docs
Requires-Dist: sphinx ; extra == 'docs'
Requires-Dist: myst-parser ; extra == 'docs'
Requires-Dist: myst-nb ; extra == 'docs'
Requires-Dist: docutils <0.18,>=0.14 ; extra == 'docs'
Requires-Dist: sphinx-autobuild ; extra == 'docs'
Requires-Dist: sphinx-copybutton ; extra == 'docs'
Requires-Dist: sphinx-inline-tabs ; extra == 'docs'
Requires-Dist: furo ; extra == 'docs'
Requires-Dist: breathe ; extra == 'docs'
Requires-Dist: setuptools-scm ; extra == 'docs'
Requires-Dist: nbdime ; extra == 'docs'
Requires-Dist: pygments >=2.4.1 ; extra == 'docs'
Requires-Dist: linkify-it-py ; extra == 'docs'
Requires-Dist: scipy ; extra == 'docs'
Requires-Dist: snek5000-tgv ; extra == 'docs'
Requires-Dist: snek5000-phill ; extra == 'docs'
Requires-Dist: snek5000-cbox ; extra == 'docs'
Provides-Extra: hpc
Requires-Dist: nox ; extra == 'hpc'
Requires-Dist: pytest ; extra == 'hpc'
Requires-Dist: coverage[toml] ; extra == 'hpc'
Requires-Dist: pytest-cov ; extra == 'hpc'
Requires-Dist: pytest-datadir ; extra == 'hpc'
Requires-Dist: pytest-mock ; extra == 'hpc'
Requires-Dist: ipython ; extra == 'hpc'
Requires-Dist: click ; extra == 'hpc'
Provides-Extra: tests
Requires-Dist: nox ; extra == 'tests'
Requires-Dist: pytest ; extra == 'tests'
Requires-Dist: coverage[toml] ; extra == 'tests'
Requires-Dist: pytest-cov ; extra == 'tests'
Requires-Dist: pytest-datadir ; extra == 'tests'
Requires-Dist: pytest-mock ; extra == 'tests'
Requires-Dist: ipython ; extra == 'tests'
